meteoredpy/__init__.py
meteoredpy/meteoredpy.py
meteoredpy-0.0.4.dist-info/LICENSE
meteoredpy-0.0.4.dist-info/METADATA
meteoredpy-0.0.4.dist-info/WHEEL
meteoredpy-0.0.4.dist-info/top_level.txt
meteoredpy-0.0.4.dist-info/RECORD
