Metadata-Version: 2.1
Name: meteoredpy
Version: 0.0.4
Summary: Libreria para consumir y parsear a JSON API de meteored.cl
Author-email: Alejandro Farías <farias@pm.me>
License: GNU GENERAL PUBLIC LICENSE
Project-URL: Homepage, https://github.com/fariascl/meteoredpy
Project-URL: Bug Tracker, https://github.com/fariascl/meteoredpy/issues
Classifier: Programming Language :: Python :: 3
Classifier: Operating System :: OS Independent
Requires-Python: >=3.6
License-File: LICENSE
Requires-Dist: requests >=2.31.0
Requires-Dist: xmltodict ==0.13.0
